localstack_s3_pyspark/__init__.py
localstack_s3_pyspark/__main__.py
localstack_s3_pyspark/boto3.py
localstack_s3_pyspark/configure_defaults.py
localstack_s3_pyspark/py.typed
localstack_s3_pyspark-0.12.6.data/data/localstack_s3_pyspark/py.typed
localstack_s3_pyspark-0.12.6.dist-info/METADATA
localstack_s3_pyspark-0.12.6.dist-info/WHEEL
localstack_s3_pyspark-0.12.6.dist-info/entry_points.txt
localstack_s3_pyspark-0.12.6.dist-info/top_level.txt
localstack_s3_pyspark-0.12.6.dist-info/RECORD
