Metadata-Version: 2.1
Name: localstack-s3-pyspark
Version: 0.12.6
Summary: A CLI to configure pyspark for use with s3 on localstack
Home-page: https://github.com/enorganic/localstack-s3-pyspark
Author-email: david@belais.me
License: MIT
Requires-Python: ~=3.8
Requires-Dist: localstack-client ~=2.5
Requires-Dist: lxml !=5.1.0,>4.8
Requires-Dist: pyspark !=2.4.7,!=2.4.8,>=2.4
Provides-Extra: all
Requires-Dist: boto3 ; extra == 'all'
Provides-Extra: boto3
Requires-Dist: boto3 ; extra == 'boto3'
